PortfolioAnalysis/PortfolioAnalysis.py
PortfolioAnalysis/__init__.py
PortfolioAnalysis-1.0.dist-info/METADATA
PortfolioAnalysis-1.0.dist-info/WHEEL
PortfolioAnalysis-1.0.dist-info/top_level.txt
PortfolioAnalysis-1.0.dist-info/RECORD
