Metadata-Version: 2.1
Name: PortfolioAnalysis
Version: 1.0
Summary: Manage configuration files
Home-page: http://qraftec.com
Author: hyojun.moon
Author-email: hyojun.moon@qraftec.com
License: MIT
Platform: UNKNOWN
Classifier: Development Status :: 3 - Alpha
Classifier: Intended Audience :: Developers
Classifier: Topic :: Software Development :: Libraries
Classifier: License :: OSI Approved :: MIT License
Classifier: Programming Language :: Python :: 3.6
